clipboard_util/__init__.py
clipboard_util/cli.py
clipboard_util/clipboard.py
clipboard_util-0.1.2.dist-info/entry_points.txt
clipboard_util-0.1.2.dist-info/WHEEL
clipboard_util-0.1.2.dist-info/METADATA
clipboard_util-0.1.2.dist-info/RECORD
